cfn_check/__init__.py
cfn_check/cli/__init__.py
cfn_check/cli/config.py
cfn_check/cli/render.py
cfn_check/cli/root.py
cfn_check/cli/validate.py
cfn_check/cli/utils/__init__.py
cfn_check/cli/utils/attributes.py
cfn_check/cli/utils/files.py
cfn_check/cli/utils/stdout.py
cfn_check/collection/__init__.py
cfn_check/collection/collection.py
cfn_check/evaluation/__init__.py
cfn_check/evaluation/errors.py
cfn_check/evaluation/evaluator.py
cfn_check/evaluation/validate.py
cfn_check/evaluation/parsing/__init__.py
cfn_check/evaluation/parsing/query_parser.py
cfn_check/evaluation/parsing/token.py
cfn_check/evaluation/parsing/token_type.py
cfn_check/evaluation/parsing/operators/__init__.py
cfn_check/evaluation/parsing/operators/value_operator.py
cfn_check/logging/__init__.py
cfn_check/logging/models.py
cfn_check/rendering/__init__.py
cfn_check/rendering/cidr_solver.py
cfn_check/rendering/renderer.py
cfn_check/rendering/utils.py
cfn_check/rendering/parsing/__init__.py
cfn_check/rendering/parsing/cloudformation_loader.py
cfn_check/rules/__init__.py
cfn_check/rules/rule.py
cfn_check/shared/__init__.py
cfn_check/shared/types.py
cfn_check/validation/__init__.py
cfn_check/validation/validator.py
cfn_check/yaml/__init__.py
cfn_check/yaml/anchor.py
cfn_check/yaml/comments.py
cfn_check/yaml/compat.py
cfn_check/yaml/composer.py
cfn_check/yaml/configobjwalker.py
cfn_check/yaml/constructor.py
cfn_check/yaml/cyaml.py
cfn_check/yaml/docinfo.py
cfn_check/yaml/dumper.py
cfn_check/yaml/emitter.py
cfn_check/yaml/error.py
cfn_check/yaml/events.py
cfn_check/yaml/loader.py
cfn_check/yaml/main.py
cfn_check/yaml/mergevalue.py
cfn_check/yaml/nodes.py
cfn_check/yaml/parser.py
cfn_check/yaml/reader.py
cfn_check/yaml/representer.py
cfn_check/yaml/resolver.py
cfn_check/yaml/scalarbool.py
cfn_check/yaml/scalarfloat.py
cfn_check/yaml/scalarint.py
cfn_check/yaml/scalarstring.py
cfn_check/yaml/scanner.py
cfn_check/yaml/serializer.py
cfn_check/yaml/tag.py
cfn_check/yaml/timestamp.py
cfn_check/yaml/tokens.py
cfn_check-0.12.1.dist-info/licenses/LICENSE
cfn_check-0.12.1.dist-info/METADATA
cfn_check-0.12.1.dist-info/WHEEL
cfn_check-0.12.1.dist-info/entry_points.txt
cfn_check-0.12.1.dist-info/top_level.txt
cfn_check-0.12.1.dist-info/RECORD
