Metadata-Version: 2.4
Name: cfn-check
Version: 0.12.1
Summary: Validate Cloud Formation
Author-email: Ada Lundhe <adalundhe@lundhe.audio>
License: MIT License
Project-URL: Homepage, https://github.com/adalundhe/cfn-check
Keywords: cloud-formation,testing,aws,cli
Classifier: Programming Language :: Python :: 3.11
Classifier: Programming Language :: Python :: 3.12
Classifier: Programming Language :: Python :: 3.13
Classifier: Operating System :: OS Independent
Requires-Python: >=3.11
License-File: LICENSE
Requires-Dist: pydantic
Requires-Dist: ruamel.yaml
Requires-Dist: hyperlight-cocoa
Requires-Dist: async-logging
Dynamic: license-file
